DESCRIPTION.md
LICENSE
MANIFEST.in
README.rst
requirements.txt
setup.cfg
setup.py
gqlib/__init__.py
gqlib/__main__.py
gqlib/handle_args.py
gqlib.egg-info/PKG-INFO
gqlib.egg-info/SOURCES.txt
gqlib.egg-info/dependency_links.txt
gqlib.egg-info/not-zip-safe
gqlib.egg-info/requires.txt
gqlib.egg-info/top_level.txt
gqlib/alignment/__init__.py
gqlib/alignment/aln_group.py
gqlib/alignment/bamreader.py
gqlib/alignment/pysam_alignment_processor.py
gqlib/annotation/__init__.py
gqlib/annotation/count_annotator.py
gqlib/annotation/count_writer.py
gqlib/bin/__init__.py
gqlib/bin/build_bed_database.py
gqlib/bin/build_custom_database.py
gqlib/bin/build_domain_database.py
gqlib/bin/build_gene_database.py
gqlib/bin/collate_counts.py
gqlib/bin/collate_studies.py
gqlib/bin/db_collate.py
gqlib/bin/split_table.py
gqlib/counters/__init__.py
gqlib/counters/alignment_counter.py
gqlib/counters/count_manager.py
gqlib/counters/region_counter.py
gqlib/counters/seq_counter.py
gqlib/db/__init__.py
gqlib/db/annotation_db.py
gqlib/db/database.py
gqlib/db/db_import.py
gqlib/db/gff_dbm.py
gqlib/db/models/__init__.py
gqlib/db/models/db.py
gqlib/db/models/meta.py
gqlib/profilers/__init__.py
gqlib/profilers/feature_quantifier.py
gqlib/profilers/gene_quantifier.py
gqlib/profilers/region_quantifier.py
gqlib/runners/__init__.py
gqlib/runners/alignment_runner.py
gqlib/ui/__init__.py
gqlib/ui/validation.py
gqlib_old/__init__.py
gqlib_old/__main__.py
gqlib_old/handle_args.py
gqlib_old/alignment/__init__.py
gqlib_old/alignment/aln_group.py
gqlib_old/alignment/bamreader.py
gqlib_old/alignment/pysam_alignment_processor.py
gqlib_old/annotation/__init__.py
gqlib_old/annotation/count_annotator.py
gqlib_old/annotation/count_writer.py
gqlib_old/bin/__init__.py
gqlib_old/bin/build_bed_database.py
gqlib_old/bin/build_custom_database.py
gqlib_old/bin/build_domain_database.py
gqlib_old/bin/build_gene_database.py
gqlib_old/bin/build_pg3_database.py
gqlib_old/bin/collate_counts.py
gqlib_old/bin/collate_studies.py
gqlib_old/bin/db_collate.py
gqlib_old/bin/db_collate2.py
gqlib_old/bin/split_table.py
gqlib_old/counters/__init__.py
gqlib_old/counters/alignment_counter.py
