Metadata-Version: 2.1
Name: gqlib
Version: 2.14.2
Summary: This is gqlib.
Home-page: https://github.com/cschu/gqlib
Author: Christian Schudoma
Author-email: cschu1981@gmail.com
License: MIT
Keywords: large reference data genomic feature quantification
Classifier: Development Status :: 4 - Beta
Classifier: Topic :: Scientific/Engineering :: Bio-Informatics
Classifier: License :: OSI Approved :: MIT License
Classifier: Operating System :: POSIX :: Linux
Classifier: Programming Language :: Python :: 3.7
Classifier: Programming Language :: Python :: 3.8
Classifier: Programming Language :: Python :: 3.9
Classifier: Programming Language :: Python :: 3.10
License-File: LICENSE
